<?xml version='1.0' encoding='utf-8'?>
<data><train><train_number>78</train_number><station_departure>Borisov</station_departure><station_arrival>Borisov</station_arrival><departure>2022.05.05-12:00</departure><arrival>2022.30.08-11:07</arrival></train><train><train_number>1</train_number><station_departure>Minsk</station_departure><station_arrival>Brest</station_arrival><departure>2022.02.05-01:00</departure><arrival>2022.02.05-06:00</arrival></train><train><train_number>2</train_number><station_departure>Gomel</station_departure><station_arrival>Vitebsk</station_arrival><departure>2022.04.05-13:00</departure><arrival>2022.05.05-11:00</arrival></train><train><train_number>3</train_number><station_departure>Polotsk</station_departure><station_arrival>Turov</station_arrival><departure>2022.07.05-23:00</departure><arrival>2022.08.05-11:00</arrival></train><train><train_number>4444</train_number><station_departure>Postavy</station_departure><station_arrival>Berlin</station_arrival><departure>2022.17.05-13:00</departure><arrival>2022.20.05-06:00</arrival></train><train><train_number>5</train_number><station_departure>Mogilev</station_departure><station_arrival>Minsk</station_arrival><departure>2022.03.05-17:00</departure><arrival>2022.03.05-22:00</arrival></train><train><train_number>1</train_number><station_departure>Brest</station_departure><station_arrival>Minsk</station_arrival><departure>2022.05.05-23:00</departure><arrival>2022.06.05-06:00</arrival></train><train><train_number>1</train_number><station_departure>Minsk</station_departure><station_arrival>Brest</station_arrival><departure>2022.07.05-14:00</departure><arrival>2022.07.05-21:00</arrival></train><train><train_number>14</train_number><station_departure>Kiuv</station_departure><station_arrival>Kharkiv</station_arrival><departure>2022.26.05-04:00</departure><arrival>2022.28.05-06:00</arrival></train><train><train_number>1503</train_number><station_departure>New-York</station_departure><station_arrival>Boston</station_arrival><departure>2022.27.05-04:15</departure><arrival>2022.27.05-17:00</arrival></train><train><train_number>7780</train_number><station_departure>Berlin</station_departure><station_arrival>Paris</station_arrival><departure>2022.30.05-13:30</departure><arrival>2022.30.05-16:45</arrival></train><train><train_number>9000</train_number><station_departure>Wroclaw</station_departure><station_arrival>Warsaw</station_arrival><departure>2022.28.05-17:00</departure><arrival>2022.28.05-20:00</arrival></train><train><train_number>44</train_number><station_departure>Riga</station_departure><station_arrival>Tallin</station_arrival><departure>2022.31.05-12:00</departure><arrival>2022.31.05-15:00</arrival></train><train><train_number>11</train_number><station_departure>Grodno</station_departure><station_arrival>Gomel</station_arrival><departure>2022.26.05-23:55</departure><arrival>2022.27.05-07:35</arrival></train><train><train_number>67</train_number><station_departure>Lublin</station_departure><station_arrival>Gdansk</station_arrival><departure>2022.28.05-08:30</departure><arrival>2022.28.05-12:00</arrival></train><train><train_number>33</train_number><station_departure>Dresden</station_departure><station_arrival>Bremen</station_arrival><departure>2022.26.05-09:00</departure><arrival>2022.26.05-15:20</arrival></train><train><train_number>888</train_number><station_departure>Lyon</station_departure><station_arrival>Paris</station_arrival><departure>2022.01.06-18:00</departure><arrival>2022.02.06-09:00</arrival></train><train><train_number>45</train_number><station_departure>Seville</station_departure><station_arrival>Malaga</station_arrival><departure>2022.26.05-01:00</departure><arrival>2022.26.05-03:00</arrival></train><train><train_number>98</train_number><station_departure>Porto</station_departure><station_arrival>Lisbon</station_arrival><departure>2022.30.05-17:00</departure><arrival>2022.30.05-21:00</arrival></train><train><train_number>23</train_number><station_departure>Zaragoza</station_departure><station_arrival>Barselona</station_arrival><departure>2022.31.05-18:00</departure><arrival>2022.31.05-21:05</arrival></train><train><train_number>65</train_number><station_departure>Montpellier</station_departure><station_arrival>Nantes</station_arrival><departure>2022.24.05-12:00</departure><arrival>2022.24.05-16:00</arrival></train><train><train_number>7609</train_number><station_departure>Glasgow</station_departure><station_arrival>London</station_arrival><departure>2022.07.05-16:15</departure><arrival>2022.08.05-01:00</arrival></train><train><train_number>9755</train_number><station_departure>Dublin</station_departure><station_arrival>Cork</station_arrival><departure>2022.12.05-15:00</departure><arrival>2022.12.05-23:55</arrival></train><train><train_number>5401</train_number><station_departure>Liverpool</station_departure><station_arrival>Brighton</station_arrival><departure>2022.19.05-18:00</departure><arrival>2022.19.05-22:40</arrival></train><train><train_number>2103</train_number><station_departure>Togliatti</station_departure><station_arrival>Rome</station_arrival><departure>2022.05.05-06:00</departure><arrival>2022.08.05-08:45</arrival></train><train><train_number>56</train_number><station_departure>Vienna</station_departure><station_arrival>Graz</station_arrival><departure>2022.27.05-14:00</departure><arrival>2022.27.05-18:00</arrival></train><train><train_number>2013</train_number><station_departure>Brno</station_departure><station_arrival>Prague</station_arrival><departure>2022.16.05-17:35</departure><arrival>2022.17.05-01:10</arrival></train><train><train_number>4545</train_number><station_departure>Nuremberg</station_departure><station_arrival>Hamburg</station_arrival><departure>2022.20.05-23:00</departure><arrival>2022.21.05-05:00</arrival></train><train><train_number>2813</train_number><station_departure>Gothenburg</station_departure><station_arrival>Stockholm</station_arrival><departure>2022.11.05-07:00</departure><arrival>2022.12.05-00:15</arrival></train><train><train_number>6819</train_number><station_departure>Helsinki</station_departure><station_arrival>Norrkoping</station_arrival><departure>2022.23.05-18:00</departure><arrival>2022.24.05-03:00</arrival></train><train><train_number>55</train_number><station_departure>Oslo</station_departure><station_arrival>Bergen</station_arrival><departure>2022.26.05-10:00</departure><arrival>2022.26.05-21:00</arrival></train><train><train_number>6745</train_number><station_departure>Brussels</station_departure><station_arrival>Paris</station_arrival><departure>2022.26.05-11:00</departure><arrival>2022.26.05-14:00</arrival></train><train><train_number>1299</train_number><station_departure>Porto</station_departure><station_arrival>Madrid</station_arrival><departure>2022.18.05-18:00</departure><arrival>2022.26.05-23:55</arrival></train><train><train_number>9009</train_number><station_departure>Bucharest</station_departure><station_arrival>Cluj - Napoca</station_arrival><departure>2022.27.05-09:00</departure><arrival>2022.27.05-16:00</arrival></train><train><train_number>8745</train_number><station_departure>Odesa</station_departure><station_arrival>Kyiv</station_arrival><departure>2022.26.05-13:00</departure><arrival>2022.26.05-22:00</arrival></train><train><train_number>3012</train_number><station_departure>Cambridge</station_departure><station_arrival>Edinburgh</station_arrival><departure>2022.28.05-10:00</departure><arrival>2022.28.05-13:00</arrival></train><train><train_number>6609</train_number><station_departure>Cardiff</station_departure><station_arrival>Leeds</station_arrival><departure>2022.11.05-15:00</departure><arrival>2022.11.05-20:00</arrival></train><train><train_number>3487</train_number><station_departure>La Rochelle</station_departure><station_arrival>Toulouse</station_arrival><departure>2022.13.05-17:00</departure><arrival>2022.13.05-23:00</arrival></train><train><train_number>2907</train_number><station_departure>Tarragona</station_departure><station_arrival>Santiago de Compostela</station_arrival><departure>2022.01.05-13:00</departure><arrival>2022.02.05-13:00</arrival></train><train><train_number>4587</train_number><station_departure>Pontevedra</station_departure><station_arrival>Murcia</station_arrival><departure>2022.10.05-17:00</departure><arrival>2022.10.05-22:00</arrival></train><train><train_number>5110</train_number><station_departure>Limoges</station_departure><station_arrival>Aix-en-Provence</station_arrival><departure>2022.27.05-18:00</departure><arrival>2022.27.05-22:00</arrival></train><train><train_number>4879</train_number><station_departure>Vigo</station_departure><station_arrival>Albufeira</station_arrival><departure>2022.21.05-06:00</departure><arrival>2022.21.05-11:00</arrival></train><train><train_number>1101</train_number><station_departure>Badajoz</station_departure><station_arrival>Granada</station_arrival><departure>2022.15.05-05:00</departure><arrival>2022.15.05-12:00</arrival></train><train><train_number>2305</train_number><station_departure>Fes</station_departure><station_arrival>Malaga</station_arrival><departure>2022.27.05-14:00</departure><arrival>2022.27.05-22:50</arrival></train><train><train_number>5161</train_number><station_departure>Lisbon</station_departure><station_arrival>Bilbao</station_arrival><departure>2022.28.05-08:00</departure><arrival>2022.28.05-17:00</arrival></train><train><train_number>7744</train_number><station_departure>Vitoria-Gasteiz</station_departure><station_arrival>Donostia-San-Sebastian</station_arrival><departure>2022.27.05-18:00</departure><arrival>2022.27.05-21:00</arrival></train><train><train_number>2501</train_number><station_departure>Geneva</station_departure><station_arrival>Bern</station_arrival><departure>2022.17.05-17:00</departure><arrival>2022.17.05-22:00</arrival></train><train><train_number>7878</train_number><station_departure>Strasbourg</station_departure><station_arrival>Saarbrucken</station_arrival><departure>2022.20.05-23:00</departure><arrival>2022.21.05-05:00</arrival></train><train><train_number>6671</train_number><station_departure>Frankfurt</station_departure><station_arrival>Garmisch-Partenkirchen</station_arrival><departure>2022.11.05-08:00</departure><arrival>2022.11.05-13:00</arrival></train><train><train_number>1000</train_number><station_departure>Pula</station_departure><station_arrival>Zagreb</station_arrival><departure>2022.05.05-16:25</departure><arrival>2022.05.05-22:00</arrival></train></data>